README.md
setup.py
reebulk/__init__.py
reebulk/main.py
reebulk.egg-info/PKG-INFO
reebulk.egg-info/SOURCES.txt
reebulk.egg-info/dependency_links.txt
reebulk.egg-info/entry_points.txt
reebulk.egg-info/requires.txt
reebulk.egg-info/top_level.txt