Metadata-Version: 1.0
Name: reebulk
Version: 0.1.1
Summary: bulk image resizer implemented in python
Home-page: UNKNOWN
Author: ahmad alwi
Author-email: ahmadalwiam@gmail.com
License: UNKNOWN
Keywords: pytohn,pillow,bulk
Platform: UNKNOWN
